borgctl/__init__.py
borgctl/default.yml.template
borgctl/helper.py
borgctl/utils.py
borgctl/wordlist.py
borgctl-0.5.0.dist-info/LICENSE
borgctl-0.5.0.dist-info/METADATA
borgctl-0.5.0.dist-info/WHEEL
borgctl-0.5.0.dist-info/entry_points.txt
borgctl-0.5.0.dist-info/RECORD
