Metadata-Version: 2.3
Name: borgctl
Version: 0.5.0
Summary: 
Author: kmille
Author-email: github@androidloves.me
Requires-Python: >=3.11,<4.0
Classifier: Programming Language :: Python :: 3
Classifier: Programming Language :: Python :: 3.11
Classifier: Programming Language :: Python :: 3.12
Classifier: Programming Language :: Python :: 3.13
Requires-Dist: ruamel-yaml (>=0.18.5,<0.19.0)
